evolvishub_datacleanup/__init__.py
evolvishub_datacleanup/config.py
evolvishub_datacleanup/manager.py
evolvishub_datacleanup/utils.py
evolvishub_datacleanup-0.1.1.dist-info/licenses/LICENSE
evolvishub_datacleanup-0.1.1.dist-info/METADATA
evolvishub_datacleanup-0.1.1.dist-info/WHEEL
evolvishub_datacleanup-0.1.1.dist-info/top_level.txt
evolvishub_datacleanup-0.1.1.dist-info/RECORD
