Metadata-Version: 2.4
Name: evolvishub-datacleanup
Version: 0.1.1
Summary: A professional data cleanup management library
Home-page: https://github.com/yourusername/evolvishub-datacleanup
Author: Alban Maxhuni, PhD
Author-email: a.maxhuni@evolvis.ai
Classifier: Development Status :: 4 - Beta
Classifier: Intended Audience :: Developers
Classifier: License :: OSI Approved :: MIT License
Classifier: Operating System :: OS Independent
Classifier: Programming Language :: Python :: 3
Classifier: Programming Language :: Python :: 3.7
Classifier: Programming Language :: Python :: 3.8
Classifier: Programming Language :: Python :: 3.9
Classifier: Programming Language :: Python :: 3.10
Classifier: Programming Language :: Python :: 3.11
Classifier: Programming Language :: Python :: 3.12
Requires-Python: >=3.7
License-File: LICENSE
Requires-Dist: PyYAML>=6.0
Requires-Dist: python-dateutil>=2.8.2
Requires-Dist: watchdog>=2.1.0
Requires-Dist: schedule>=1.1.0
Requires-Dist: rarfile>=4.0
Requires-Dist: python-magic>=0.4.27
Provides-Extra: dev
Requires-Dist: pytest>=7.0; extra == "dev"
Requires-Dist: pytest-cov>=4.0; extra == "dev"
Requires-Dist: black>=22.0; extra == "dev"
Requires-Dist: isort>=5.0; extra == "dev"
Requires-Dist: mypy>=1.0; extra == "dev"
Requires-Dist: flake8>=6.0; extra == "dev"
Dynamic: author
Dynamic: author-email
Dynamic: classifier
Dynamic: description
Dynamic: description-content-type
Dynamic: home-page
Dynamic: license-file
Dynamic: provides-extra
Dynamic: requires-dist
Dynamic: requires-python
Dynamic: summary
